setup.py
tuda_distributions/Binomialdistribution.py
tuda_distributions/Gaussiandistribution.py
tuda_distributions/Generaldistribution.py
tuda_distributions/__init__.py
tuda_distributions.egg-info/PKG-INFO
tuda_distributions.egg-info/SOURCES.txt
tuda_distributions.egg-info/dependency_links.txt
tuda_distributions.egg-info/not-zip-safe
tuda_distributions.egg-info/top_level.txt