Metadata-Version: 1.0
Name: tuda-distributions
Version: 0.1
Summary: Gaussian and Binomial distributions
Home-page: UNKNOWN
Author: Richa Jain
Author-email: richajain44@gmail.com
License: UNKNOWN
Platform: UNKNOWN
